minify/__init__.py
minify/_ffi_minify.py
minify/minify.so
tdewolff_minify-2.24.8.dist-info/METADATA
tdewolff_minify-2.24.8.dist-info/WHEEL
tdewolff_minify-2.24.8.dist-info/top_level.txt
tdewolff_minify-2.24.8.dist-info/RECORD
